horton_grid/__init__.py
horton_grid/_version.py
horton_grid/cache.py
horton_grid/cell.cpp
horton_grid/cell.h
horton_grid/cell.pxd
horton_grid/cext.cpython-310-darwin.so
horton_grid/cext.pxd
horton_grid/cext.pyx
horton_grid/constants.py
horton_grid/context.py
horton_grid/context.py.bak
horton_grid/exceptions.py
horton_grid/log.py
horton_grid/moments.cpp
horton_grid/moments.h
horton_grid/moments.pxd
horton_grid/moments.py
horton_grid/nucpot.cpp
horton_grid/nucpot.h
horton_grid/nucpot.pxd
horton_grid/periodic.py
horton_grid/quadprog.py
horton_grid/units.py
horton_grid/utils.py
horton_grid/data/elements.csv
horton_grid/data/references.bib
horton_grid/data/examples/expectation_r.py
horton_grid/data/grids/tv-13.7-3.txt
horton_grid/data/grids/tv-13.7-4.txt
horton_grid/data/grids/tv-13.7-5.txt
horton_grid/data/grids/tv-13.7-6.txt
horton_grid/data/grids/tv-13.7-7.txt
horton_grid/data/grids/tv-13.7-8.txt
horton_grid/data/test/2h-azirine-cc.fchk
horton_grid/data/test/2h-azirine-ci.fchk
horton_grid/data/test/2h-azirine-mp2.fchk
horton_grid/data/test/2h-azirine-mp3.fchk
horton_grid/data/test/2h-azirine.xyz
horton_grid/data/test/CHGCAR.oxygen
horton_grid/data/test/CHGCAR.water
horton_grid/data/test/F.molden
horton_grid/data/test/FCIDUMP.molpro.h2
horton_grid/data/test/FCIDUMP.molpro.h2-erf
horton_grid/data/test/FCIDUMP.psi4.h2
horton_grid/data/test/LOCPOT.oxygen
horton_grid/data/test/POSCAR.cubicbn_cartesian
horton_grid/data/test/POSCAR.cubicbn_direct
horton_grid/data/test/POSCAR.water
horton_grid/data/test/aelta.cube
horton_grid/data/test/atom_001_001_hf_lan.fchk
horton_grid/data/test/atom_001_001_hf_sto3g.fchk
horton_grid/data/test/atom_001_002_hf_lan.fchk
horton_grid/data/test/atom_001_002_hf_sto3g.fchk
horton_grid/data/test/atom_006_005_hf_sto3g.fchk
horton_grid/data/test/atom_006_006_hf_sto3g.fchk
horton_grid/data/test/atom_006_007_hf_sto3g.fchk
horton_grid/data/test/atom_008_007_hf_lan.fchk
horton_grid/data/test/atom_008_007_hf_sto3g.fchk
horton_grid-0.0.3.dist-info/COPYING
horton_grid-0.0.3.dist-info/METADATA
horton_grid-0.0.3.dist-info/WHEEL
horton_grid-0.0.3.dist-info/top_level.txt
horton_grid-0.0.3.dist-info/RECORD
