Metadata-Version: 2.1
Name: horton-grid
Version: 0.0.3
Summary: Molecular grids used in computational chemistry
Author-email: YingXing Cheng <yingxing.cheng@ugent.be>, Toon Verstraelen <toon.verstraelen@ugent.be>
License: GNU GENERAL PUBLIC LICENSE
Classifier: Development Status :: 3 - Alpha
Classifier: Environment :: Console
Classifier: Intended Audience :: Science/Research
Classifier: Intended Audience :: Education
Classifier: Framework :: Matplotlib
Classifier: License :: OSI Approved :: GNU General Public License v3 or later (GPLv3+)
Classifier: Natural Language :: English
Classifier: Operating System :: POSIX
Classifier: Operating System :: MacOS
Classifier: Programming Language :: Python :: 3
Classifier: Topic :: Scientific/Engineering
Requires-Python: >=3.10
License-File: COPYING
Requires-Dist: numpy
Requires-Dist: pre-commit
Requires-Dist: pytest
Requires-Dist: nose
Requires-Dist: scipy
Requires-Dist: h5py
